general_text_classifier/__init__.py
general_text_classifier-0.1.28.dist-info/LICENSE.txt
general_text_classifier-0.1.28.dist-info/METADATA
general_text_classifier-0.1.28.dist-info/WHEEL
general_text_classifier-0.1.28.dist-info/top_level.txt
general_text_classifier-0.1.28.dist-info/RECORD
