Metadata-Version: 2.1
Name: general-text-classifier
Version: 0.1.28
Summary: General Text Classification Library
Home-page: UNKNOWN
Author: Trendyol NLP Team
License: UNKNOWN
Platform: UNKNOWN
Classifier: License :: OSI Approved :: MIT License
Classifier: Operating System :: OS Independent
Classifier: Programming Language :: Python :: 3.7
License-File: LICENSE.txt
Requires-Dist: wandb (>=0.13.3)
Requires-Dist: google-cloud-bigquery (>=3.3.2)
Requires-Dist: google-cloud-bigquery[pandas]
Requires-Dist: google-cloud-storage (>=2.5.0)
Requires-Dist: google-cloud-core (>=2.3.2)
Requires-Dist: google-resumable-media (>=2.3.3)
Requires-Dist: iterative-stratification (>=0.1.7)
Requires-Dist: transformers (>=4.6.1)
Requires-Dist: torch (>=1.7.1)
Requires-Dist: regex (>=2022.6.2)
Requires-Dist: scikit-learn (>=0.24.2)
Requires-Dist: streamlit (>=0.82.0)
Requires-Dist: datasets (>=2.3.2)
Requires-Dist: tensorboardX (>=2.2)
Requires-Dist: tokenizers (>=0.10.3)
Requires-Dist: seqeval (>=1.2.2)
Requires-Dist: sentencepiece (>=0.1.95)
Requires-Dist: tqdm (>=4.47.0)
Requires-Dist: requests (>=2.25.1)
Requires-Dist: scipy (>=1.7.3)
Requires-Dist: simpletransformers (>=0.61.6)
